format_seismo/__init__.py
format_seismo/format_seismo.py
format_seismo-0.1.1.dist-info/licenses/LICENSE
format_seismo-0.1.1.dist-info/METADATA
format_seismo-0.1.1.dist-info/WHEEL
format_seismo-0.1.1.dist-info/top_level.txt
format_seismo-0.1.1.dist-info/RECORD
