Metadata-Version: 2.4
Name: format_seismo
Version: 0.1.1
Summary: A Python package for preprocessing seismological data
Home-page: https://github.com/DomagojHrvojevic/format_seismo
Author: DomagojHrvojevic
Author-email: Domagoj Hrvojevic <domagoj@example.com>
License-Expression: MIT
Requires-Python: >=3.8
License-File: LICENSE
Requires-Dist: obspy
Requires-Dist: numpy
Dynamic: author
Dynamic: home-page
Dynamic: license-file
Dynamic: requires-python
